textuscore/__init__.py
textuscore-0.0.1.dist-info/METADATA
textuscore-0.0.1.dist-info/WHEEL
textuscore-0.0.1.dist-info/RECORD
